task2/rom.sv
module rom #(
    parameter   ADDRESS_WIDTH = 8,
                DATA_WIDTH = 8
)(
    input logic                     clk,
    input logic [ADDRESS_WIDTH-1:0] addr1,
    input logic [ADDRESS_WIDTH-1:0] addr2,
    output logic [DATA_WIDTH-1:0]   dout1,
    output logic [DATA_WIDTH-1:0]   dout2
);

logic [DATA_WIDTH-1:0] rom_array [2**ADDRESS_WIDTH-1:0];

initial begin
        $display("Loading rom.");
        $readmemh("sinerom.mem", rom_array);
end;

always_ff @(posedge clk) begin
    //output is synchronous
    dout1 <= rom_array [addr1];
    dout2 <= rom_array [addr2];
end

endmodule

task2/counter.sv
module counter #(
    parameter WIDTH = 8
)(
    //Interface signals
    input logic             clk,    //clock
    input logic             rst,    //reset
    input logic             en,     //counter enable
    input logic             incr,
    output logic [WIDTH-1:0] count   //counter output
);

always_ff @ (posedge clk)
    if (rst)    count <= {WIDTH{1'b0}};
    else        count <= count + {{WIDTH - 1 {1'b0}}, incr};

endmodule

task2/sinegen.sv
module sinegen #(
    parameter   A_WIDTH = 8,
    parameter   D_WIDTH = 8
)(
    //interface signals
    input logic                 clk,
    input logic                 rst,
    input logic                 en,
    input logic [A_WIDTH-1:0]   phase,
    input logic                 incr,   //increment for output counter
    output logic [D_WIDTH-1:0]  dout1,    //output data
    output logic [D_WIDTH-1:0]  dout2
);

    logic [A_WIDTH-1:0]         address; //interconnect wire

counter addrCounter (
    .clk (clk),
    .rst (rst),
    .en (en),
    .incr (incr),
    .count (address)
);

rom sinRom (
    .clk (clk),
    .addr1 (address),
    .dout1 (dout1),
    .addr2 (address + phase),
    .dout2 (dout2)
);

endmodule

task2/sinegen.vcd
$version Generated by VerilatedVcd $end
$date Sat Nov  2 21:16:00 2024 $end
$timescale 1ps $end

 $scope module TOP $end
  $var wire  1 # clk $end
  $var wire  8 ( dout1 [7:0] $end
  $var wire  8 ) dout2 [7:0] $end
  $var wire  1 % en $end
  $var wire  1 ' incr $end
  $var wire  8 & phase [7:0] $end
  $var wire  1 $ rst $end
  $scope module sinegen $end
   $var wire 32 , A_WIDTH [31:0] $end
   $var wire 32 , D_WIDTH [31:0] $end
   $var wire  8 * address [7:0] $end
   $var wire  1 # clk $end
   $var wire  8 ( dout1 [7:0] $end
   $var wire  8 ) dout2 [7:0] $end
   $var wire  1 % en $end
   $var wire  1 ' incr $end
   $var wire  8 & phase [7:0] $end
   $var wire  1 $ rst $end
   $scope module addrCounter $end
    $var wire 32 , WIDTH [31:0] $end
    $var wire  1 # clk $end
    $var wire  8 * count [7:0] $end
    $var wire  1 % en $end
    $var wire  1 ' incr $end
    $var wire  1 $ rst $end
   $upscope $end
   $scope module sinRom $end
    $var wire 32 , ADDRESS_WIDTH [31:0] $end
    $var wire 32 , DATA_WIDTH [31:0] $end
    $var wire  8 * addr1 [7:0] $end
    $var wire  8 + addr2 [7:0] $end
    $var wire  1 # clk $end
    $var wire  8 ( dout1 [7:0] $end
    $var wire  8 ) dout2 [7:0] $end
   $upscope $end
  $upscope $end
 $upscope $end
$enddefinitions $end


#0
1#
1$
0%
b00000000 &
1'
b00000000 (
b00000000 )
b00000000 *
b00000000 +
b00000000000000000000000000001000 ,
#2
0#
b00110011 &
b11111110 (
b11111110 )
b00110011 +
#4
b10100110 )
#6
0$
#8
b00000001 *
b00110100 +
#10
b11111101 (
b10100011 )
b00000010 *
b00110101 +
#12
1%
b10100000 )
b00000011 *
b00110110 +
#14
b10011101 )
b00000100 *
b00110111 +
#16
b10011010 )
b00000101 *
b00111000 +
#18
b10010111 )
b00000110 *
b00111001 +
#20
b11111100 (
b10010100 )
b00000111 *
b00111010 +
#22
b10010001 )
b00001000 *
b00111011 +
#24
b11111011 (
b10001110 )
b00001001 *
b00111100 +
#26
b11111010 (
b10001011 )
b00001010 *
b00111101 +
#28
b10001000 )
b00001011 *
b00111110 +
#30
b11111001 (
b10000101 )
b00001100 *
b00111111 +
#32
1$
b11111000 (
b10000010 )
b00001101 *
b01000000 +
#34
0$
b11110111 (
b01111110 )
b00000000 *
b00110011 +
#36
b11111110 (
b10100110 )
b00000001 *
b00110100 +
#38
b11111101 (
b10100011 )
b00000010 *
b00110101 +
#40
b10100000 )
b00000011 *
b00110110 +
#42
b10011101 )
b00000100 *
b00110111 +
#44
b10011010 )
b00000101 *
b00111000 +
#46
b10010111 )
b00000110 *
b00111001 +
#48
b11111100 (
b10010100 )
b00000111 *
b00111010 +
#50
b10010001 )
b00001000 *
b00111011 +
#52
b11111011 (
b10001110 )
b00001001 *
b00111100 +
#54
b11111010 (
b10001011 )
b00001010 *
b00111101 +
#56
b10001000 )
b00001011 *
b00111110 +
#58
b11111001 (
b10000101 )
b00001100 *
b00111111 +
#60
b11111000 (
b10000010 )
b00001101 *
b01000000 +
#62
b11110111 (
b01111110 )
b00001110 *
b01000001 +
#64
b11110110 (
b01111011 )
b00001111 *
b01000010 +
#66
b11110101 (
b01111000 )
b00010000 *
b01000011 +
#68
b11110100 (
b01110101 )
b00010001 *
b01000100 +
#70
b11110011 (
b01110010 )
b00010010 *
b01000101 +
#72
b11110001 (
b01101111 )
b00010011 *
b01000110 +
#74
b11110000 (
b01101100 )
b00010100 *
b01000111 +
#76
b11101111 (
b01101001 )
b00010101 *
b01001000 +
#78
b11101101 (
b01100110 )
b00010110 *
b01001001 +
#80
b11101011 (
b01100011 )
b00010111 *
b01001010 +
#82
b11101010 (
b01100000 )
b00011000 *
b01001011 +
#84
b11101000 (
b01011101 )
b00011001 *
b01001100 +
#86
b11100110 (
b01011010 )
b00011010 *
b01001101 +
#88
b11100101 (
b01010111 )
b00011011 *
b01001110 +
#90
b11100011 (
b01010100 )
b00011100 *
b01001111 +
#92
b11100001 (
b01010001 )
b00011101 *
b01010000 +
#94
b11011111 (
b01001110 )
b00011110 *
b01010001 +
#96
b11011101 (
b01001011 )
b00011111 *
b01010010 +
#98
b11011010 (
b01001000 )
b00100000 *
b01010011 +
#100
b11011000 (
b01000101 )
b00100001 *
b01010100 +
#102
b11010110 (
b01000011 )
b00100010 *
b01010101 +
#104
b11010100 (
b01000000 )
b00100011 *
b01010110 +
#106
b11010001 (
b00111101 )
b00100100 *
b01010111 +
#108
b11001111 (
b00111011 )
b00100101 *
b01011000 +
#110
b11001101 (
b00111000 )
b00100110 *
b01011001 +
#112
b11001010 (
b00110101 )
b00100111 *
b01011010 +
#114
b11001000 (
b00110011 )
b00101000 *
b01011011 +
#116
b11000101 (
b00110000 )
b00101001 *
b01011100 +
#118
b11000010 (
b00101110 )
b00101010 *
b01011101 +
#120
b11000000 (
b00101100 )
b00101011 *
b01011110 +
#122
b10111101 (
b00101001 )
b00101100 *
b01011111 +
#124
b10111010 (
b00100111 )
b00101101 *
b01100000 +
#126
b10111000 (
b00100101 )
b00101110 *
b01100001 +
#128
b10110101 (
b00100011 )
b00101111 *
b01100010 +
#130
b10110010 (
b00100000 )
b00110000 *
b01100011 +
#132
b10101111 (
b00011110 )
b00110001 *
b01100100 +
#134
b10101100 (
b00011100 )
b00110010 *
b01100101 +
#136
b10101001 (
b00011010 )
b00110011 *
b01100110 +
#138
b10100110 (
b00011000 )
b00110100 *
b01100111 +
#140
b10100011 (
b00010111 )
b00110101 *
b01101000 +
#142
b10100000 (
b00010101 )
b00110110 *
b01101001 +
#144
b10011101 (
b00010011 )
b00110111 *
b01101010 +
#146
b10011010 (
b00010010 )
b00111000 *
b01101011 +
#148
b10010111 (
b00010000 )
b00111001 *
b01101100 +
#150
b10010100 (
b00001110 )
b00111010 *
b01101101 +
#152
b10010001 (
b00001101 )
b00111011 *
b01101110 +
#154
b10001110 (
b00001100 )
b00111100 *
b01101111 +
#156
b10001011 (
b00001010 )
b00111101 *
b01110000 +
#158
b10001000 (
b00001001 )
b00111110 *
b01110001 +
#160
b10000101 (
b00001000 )
b00111111 *
b01110010 +
#162
b10000010 (
b00000111 )
b01000000 *
b01110011 +
#164
b01111110 (
b00000110 )
b01000001 *
b01110100 +
#166
b01111011 (
b00000101 )
b01000010 *
b01110101 +
#168
b01111000 (
b00000100 )
b01000011 *
b01110110 +
#170
b01110101 (
b00000011 )
b01000100 *
b01110111 +
#172
b01110010 (
b01000101 *
b01111000 +
#174
b01101111 (
b00000010 )
b01000110 *
b01111001 +
#176
b01101100 (
b00000001 )
b01000111 *
b01111010 +
#178
b01101001 (
b01001000 *
b01111011 +
#180
b01100110 (
b00000000 )
b01001001 *
b01111100 +
#182
b01100011 (
b01001010 *
b01111101 +
#184
b01100000 (
b01001011 *
b01111110 +
#186
b01011101 (
b01001100 *
b01111111 +
#188
b01011010 (
b01001101 *
b10000000 +
#190
b01010111 (
b01001110 *
b10000001 +
#192
b01010100 (
b01001111 *
b10000010 +
#194
b01010001 (
b01010000 *
b10000011 +
#196
b01001110 (
b01010001 *
b10000100 +
#198
b01001011 (
b01010010 *
b10000101 +
#200
b01001000 (
b01010011 *
b10000110 +
#202
b01000101 (
b00000001 )
b01010100 *
b10000111 +
#204
b01000011 (
b01010101 *
b10001000 +
#206
b01000000 (
b00000010 )
b01010110 *
b10001001 +
#208
b00111101 (
b00000011 )
b01010111 *
b10001010 +
#210
b00111011 (
b01011000 *
b10001011 +
#212
b00111000 (
b00000100 )
b01011001 *
b10001100 +
#214
b00110101 (
b00000101 )
b01011010 *
b10001101 +
#216
b00110011 (
b00000110 )
b01011011 *
b10001110 +
#218
b00110000 (
b00000111 )
b01011100 *
b10001111 +
#220
b00101110 (
b00001000 )
b01011101 *
b10010000 +
#222
b00101100 (
b00001001 )
b01011110 *
b10010001 +
#224
b00101001 (
b00001010 )
b01011111 *
b10010010 +
#226
b00100111 (
b00001100 )
b01100000 *
b10010011 +
#228
b00100101 (
b00001101 )
b01100001 *
b10010100 +
#230
b00100011 (
b00001110 )
b01100010 *
b10010101 +
#232
b00100000 (
b00010000 )
b01100011 *
b10010110 +
#234
b00011110 (
b00010010 )
b01100100 *
b10010111 +
#236
b00011100 (
b00010011 )
b01100101 *
b10011000 +
#238
b00011010 (
b00010101 )
b01100110 *
b10011001 +
#240
b00011000 (
b00010111 )
b01100111 *
b10011010 +
#242
b00010111 (
b00011000 )
b01101000 *
b10011011 +
#244
b00010101 (
b00011010 )
b01101001 *
b10011100 +
#246
b00010011 (
b00011100 )
b01101010 *
b10011101 +
#248
b00010010 (
b00011110 )
b01101011 *
b10011110 +
#250
b00010000 (
b00100000 )
b01101100 *
b10011111 +
#252
b00001110 (
b00100011 )
b01101101 *
b10100000 +
#254
b00001101 (
b00100101 )
b01101110 *
b10100001 +
#256
b00001100 (
b00100111 )
b01101111 *
b10100010 +
#258
b00001010 (
b00101001 )
b01110000 *
b10100011 +
#260
b00001001 (
b00101100 )
b01110001 *
b10100100 +
#262
b00001000 (
b00101110 )
b01110010 *
b10100101 +
#264
b00000111 (
b00110000 )
b01110011 *
b10100110 +
#266
b00000110 (
b00110011 )
b01110100 *
b10100111 +
#268
b00000101 (
b00110101 )
b01110101 *
b10101000 +
#270
b00000100 (
b00111000 )
b01110110 *
b10101001 +
#272
b00000011 (
b00111011 )
b01110111 *
b10101010 +
#274
b00111101 )
b01111000 *
b10101011 +
#276
b00000010 (
b01000000 )
b01111001 *
b10101100 +
#278
b00000001 (
b01000011 )
b01111010 *
b10101101 +
#280
b01000101 )
b01111011 *
b10101110 +
#282
b00000000 (
b01001000 )
b01111100 *
b10101111 +
#284
b01001011 )
b01111101 *
b10110000 +
#286
b01001110 )
b01111110 *
b10110001 +
#288
b01010001 )
b01111111 *
b10110010 +
#290
b01010100 )
b10000000 *
b10110011 +
#292
b01010111 )
b10000001 *
b10110100 +
#294
b01011010 )
b10000010 *
b10110101 +
#296
b01011101 )
b10000011 *
b10110110 +
#298
b01100000 )
b10000100 *
b10110111 +
#300
b01100011 )
b10000101 *
b10111000 +
#302
b01100110 )
b10000110 *
b10111001 +
#304
b00000001 (
b01101001 )
b10000111 *
b10111010 +
#306
b01101100 )
b10001000 *
b10111011 +
#308
b00000010 (
b01101111 )
b10001001 *
b10111100 +
#310
b00000011 (
b01110010 )
b10001010 *
b10111101 +
#312
b01110101 )
b10001011 *
b10111110 +
#314
b00000100 (
b01111000 )
b10001100 *
b10111111 +
#316
b00000101 (
b01111011 )
b10001101 *
b11000000 +
#318
b00000110 (
b01111111 )
b10001110 *
b11000001 +
#320
b00000111 (
b10000010 )
b10001111 *
b11000010 +
#322
b00001000 (
b10000101 )
b10010000 *
b11000011 +
#324
b00001001 (
b10001000 )
b10010001 *
b11000100 +
#326
b00001010 (
b10001011 )
b10010010 *
b11000101 +
#328
b00001100 (
b10001110 )
b10010011 *
b11000110 +
#330
b00001101 (
b10010001 )
b10010100 *
b11000111 +
#332
b00001110 (
b10010100 )
b10010101 *
b11001000 +
#334
b00010000 (
b10010111 )
b10010110 *
b11001001 +
#336
b00010010 (
b10011010 )
b10010111 *
b11001010 +
#338
b00010011 (
b10011101 )
b10011000 *
b11001011 +
#340
b00010101 (
b10100000 )
b10011001 *
b11001100 +
#342
b00010111 (
b10100011 )
b10011010 *
b11001101 +
#344
b00011000 (
b10100110 )
b10011011 *
b11001110 +
#346
b00011010 (
b10101001 )
b10011100 *
b11001111 +
#348
b00011100 (
b10101100 )
b10011101 *
b11010000 +
#350
b00011110 (
b10101111 )
b10011110 *
b11010001 +
#352
b00100000 (
b10110010 )
b10011111 *
b11010010 +
#354
b00100011 (
b10110101 )
b10100000 *
b11010011 +
#356
b00100101 (
b10111000 )
b10100001 *
b11010100 +
#358
b00100111 (
b10111010 )
b10100010 *
b11010101 +
#360
b00101001 (
b10111101 )
b10100011 *
b11010110 +
#362
b00101100 (
b11000000 )
b10100100 *
b11010111 +
#364
b00101110 (
b11000010 )
b10100101 *
b11011000 +
#366
b00110000 (
b11000101 )
b10100110 *
b11011001 +
#368
b00110011 (
b11001000 )
b10100111 *
b11011010 +
#370
b00110101 (
b11001010 )
b10101000 *
b11011011 +
#372
b00111000 (
b11001101 )
b10101001 *
b11011100 +
#374
b00111011 (
b11001111 )
b10101010 *
b11011101 +
#376
b00111101 (
b11010001 )
b10101011 *
b11011110 +
#378
b01000000 (
b11010100 )
b10101100 *
b11011111 +
#380
b01000011 (
b11010110 )
b10101101 *
b11100000 +
#382
b00110100 &
b01000101 (
b11011000 )
b10101110 *
b11100010 +
#384
b01001000 (
b11011101 )
b10101111 *
b11100011 +
#386
b00110101 &
b01001011 (
b11011111 )
b10110000 *
b11100101 +
#388
b00110110 &
b01001110 (
b11100011 )
b10110001 *
b11100111 +
#390
b01010001 (
b11100110 )
b10110010 *
b11101000 +
#392
b00110111 &
b01010100 (
b11101000 )
b10110011 *
b11101010 +
#394
b01010111 (
b11101011 )
b10110100 *
b11101011 +
#396
b00111000 &
b01011010 (
b11101101 )
b10110101 *
b11101101 +
#398
b01011101 (
b11110000 )
b10110110 *
b11101110 +
#400
b00111001 &
b01100000 (
b11110001 )
b10110111 *
b11110000 +
#402
b01100011 (
b11110100 )
b10111000 *
b11110001 +
#404
b00111010 &
b01100110 (
b11110101 )
b10111001 *
b11110011 +
#406
b01101001 (
b11110111 )
b10111010 *
b11110100 +
#408
b00111011 &
b01101100 (
b11111000 )
b10111011 *
b11110110 +
#410
b01101111 (
b11111010 )
b10111100 *
b11110111 +
#412
b01110010 (
b10111101 *
b11111000 +
#414
b01110101 (
b11111011 )
b10111110 *
b11111001 +
#416
b01111000 (
b11111100 )
b10111111 *
b11111010 +
#418
b01111011 (
b11000000 *
b11111011 +
#420
b01111111 (
b11111101 )
b11000001 *
b11111100 +
#422
b10000010 (
b11000010 *
b11111101 +
#424
b10000101 (
b11000011 *
b11111110 +
#426
b10001000 (
b11000100 *
b11111111 +
#428
b10001011 (
b11000101 *
b00000000 +
#430
b10001110 (
b11111110 )
b11000110 *
b00000001 +
#432
b10010001 (
b11111101 )
b11000111 *
b00000010 +
#434
b10010100 (
b11001000 *
b00000011 +
#436
b10010111 (
b11001001 *
b00000100 +
#438
b10011010 (
b11001010 *
b00000101 +
#440
b10011101 (
b11001011 *
b00000110 +
#442
b00111010 &
b10100000 (
b11111100 )
b11001100 *
#444
b00111000 &
b10100011 (
b11001101 *
b00000101 +
#446
b00110110 &
b10100110 (
b11111101 )
b11001110 *
b00000100 +
#448
b00110100 &
b10101001 (
b11001111 *
b00000011 +
#450
b00110011 &
b10101100 (
b11010000 *
#452
b00110010 &
b10101111 (
b11010001 *
#454
b10110010 (
b11010010 *
b00000100 +
#456
b10110101 (
b11010011 *
b00000101 +
#458
b10111000 (
b11010100 *
b00000110 +
#460
b10111010 (
b11111100 )
b11010101 *
b00000111 +
#462
b10111101 (
b11010110 *
b00001000 +
#464
b11000000 (
b11111011 )
b11010111 *
b00001001 +
#466
b11000010 (
b11111010 )
b11011000 *
b00001010 +
#468
b11000101 (
b11011001 *
b00001011 +
#470
b11001000 (
b11111001 )
b11011010 *
b00001100 +
#472
b11001010 (
b11111000 )
b11011011 *
b00001101 +
#474
b11001101 (
b11110111 )
b11011100 *
b00001110 +
#476
b11001111 (
b11110110 )
b11011101 *
b00001111 +
#478
b11010001 (
b11110101 )
b11011110 *
b00010000 +
#480
b11010100 (
b11110100 )
b11011111 *
b00010001 +
#482
b11010110 (
b11110011 )
b11100000 *
b00010010 +
#484
b11011000 (
b11110001 )
b11100001 *
b00010011 +
#486
b11011010 (
b11110000 )
b11100010 *
b00010100 +
#488
b11011101 (
b11101111 )
b11100011 *
b00010101 +
#490
b11011111 (
b11101101 )
b11100100 *
b00010110 +
#492
b11100001 (
b11101011 )
b11100101 *
b00010111 +
#494
b11100011 (
b11101010 )
b11100110 *
b00011000 +
#496
b11100101 (
b11101000 )
b11100111 *
b00011001 +
#498
b11100110 (
b11100110 )
b11101000 *
b00011010 +
#500
b11101000 (
b11100101 )
b11101001 *
b00011011 +
#502
b11101010 (
b11100011 )
b11101010 *
b00011100 +
#504
b11101011 (
b11100001 )
b11101011 *
b00011101 +
#506
b11101101 (
b11011111 )
b11101100 *
b00011110 +
#508
b11101111 (
b11011101 )
b11101101 *
b00011111 +
#510
b11110000 (
b11011010 )
b11101110 *
b00100000 +
#512
b00110001 &
b11110001 (
b11011000 )
b11101111 *
#514
b11110011 (
b11110000 *
b00100001 +
#516
b11110100 (
b11010110 )
b11110001 *
b00100010 +
#518
b11110101 (
b11010100 )
b11110010 *
b00100011 +
#520
b11110110 (
b11010001 )
b11110011 *
b00100100 +
#522
b11110111 (
b11001111 )
b11110100 *
b00100101 +
#524
b00110000 &
b11111000 (
b11001101 )
b11110101 *
#526
b11111001 (
b11110110 *
b00100110 +
#528
b11111010 (
b11001010 )
b11110111 *
b00100111 +
#530
b11001000 )
b11111000 *
b00101000 +
#532
b00101111 &
b11111011 (
b11000101 )
b11111001 *
#534
b11111100 (
b11111010 *
b00101001 +
#536
b00101110 &
b11000010 )
b11111011 *
#538
b00101101 &
b11111101 (
b11111100 *
#540
b00101100 &
b11111101 *
#542
b00101011 &
b11111110 *
#544
b00101010 &
b11111111 *
#546
b00101001 &
b00000000 *
#548
b11111110 (
b00000001 *
b00101010 +
#550
b11111101 (
b11000000 )
b00000010 *
b00101011 +
#552
b10111101 )
b00000011 *
b00101100 +
#554
b10111010 )
b00000100 *
b00101101 +
#556
b10111000 )
b00000101 *
b00101110 +
#558
b10110101 )
b00000110 *
b00101111 +
#560
b11111100 (
b10110010 )
b00000111 *
b00110000 +
#562
b10101111 )
b00001000 *
b00110001 +
#564
b11111011 (
b10101100 )
b00001001 *
b00110010 +
#566
b11111010 (
b10101001 )
b00001010 *
b00110011 +
#568
b10100110 )
b00001011 *
b00110100 +
#570
b11111001 (
b10100011 )
b00001100 *
b00110101 +
#572
b11111000 (
b10100000 )
b00001101 *
b00110110 +
#574
b00101000 &
b11110111 (
b10011101 )
b00001110 *
#576
b00100111 &
b11110110 (
b00001111 *
#578
b00100110 &
b11110101 (
b00010000 *
#580
b00100100 &
b11110100 (
b00010001 *
b00110101 +
#582
b00100010 &
b11110011 (
b10100000 )
b00010010 *
b00110100 +
#584
b00100001 &
b11110001 (
b10100011 )
b00010011 *
#586
b11110000 (
b00010100 *
b00110101 +
#588
b11101111 (
b10100000 )
b00010101 *
b00110110 +
#590
b11101101 (
b10011101 )
b00010110 *
b00110111 +
#592
b11101011 (
b10011010 )
b00010111 *
b00111000 +
#594
b11101010 (
b10010111 )
b00011000 *
b00111001 +
#596
b11101000 (
b10010100 )
b00011001 *
b00111010 +
#598
b11100110 (
b10010001 )
b00011010 *
b00111011 +
#600
b11100101 (
b10001110 )
b00011011 *
b00111100 +
#602
b11100011 (
b10001011 )
b00011100 *
b00111101 +
#604
b11100001 (
b10001000 )
b00011101 *
b00111110 +
#606
b11011111 (
b10000101 )
b00011110 *
b00111111 +
#608
b11011101 (
b10000010 )
b00011111 *
b01000000 +
#610
b11011010 (
b01111110 )
b00100000 *
b01000001 +
#612
b11011000 (
b01111011 )
b00100001 *
b01000010 +
#614
b11010110 (
b01111000 )
b00100010 *
b01000011 +
#616
b11010100 (
b01110101 )
b00100011 *
b01000100 +
#618
b11010001 (
b01110010 )
b00100100 *
b01000101 +
#620
b00100000 &
b11001111 (
b01101111 )
b00100101 *
#622
b00011111 &
b11001101 (
b00100110 *
#624
b00011110 &
b11001010 (
b00100111 *
#626
b00011101 &
b11001000 (
b00101000 *
#628
b00011100 &
b11000101 (
b00101001 *
#630
b00011010 &
b11000010 (
b00101010 *
b01000100 +
#632
b00011001 &
b11000000 (
b01110010 )
b00101011 *
#634
b00011000 &
b10111101 (
b00101100 *
#636
b00010111 &
b10111010 (
b00101101 *
#638
b10111000 (
b00101110 *
b01000101 +
#640
b10110101 (
b01101111 )
b00101111 *
b01000110 +
#642
b10110010 (
b01101100 )
b00110000 *
b01000111 +
#644
b10101111 (
b01101001 )
b00110001 *
b01001000 +
#646
b10101100 (
b01100110 )
b00110010 *
b01001001 +
#648
b10101001 (
b01100011 )
b00110011 *
b01001010 +
#650
b10100110 (
b01100000 )
b00110100 *
b01001011 +
#652
b10100011 (
b01011101 )
b00110101 *
b01001100 +
#654
b10100000 (
b01011010 )
b00110110 *
b01001101 +
#656
b10011101 (
b01010111 )
b00110111 *
b01001110 +
#658
b10011010 (
b01010100 )
b00111000 *
b01001111 +
#660
b10010111 (
b01010001 )
b00111001 *
b01010000 +
#662
b10010100 (
b01001110 )
b00111010 *
b01010001 +
#664
b10010001 (
b01001011 )
b00111011 *
b01010010 +
#666
b10001110 (
b01001000 )
b00111100 *
b01010011 +
#668
b10001011 (
b01000101 )
b00111101 *
b01010100 +
#670
b10001000 (
b01000011 )
b00111110 *
b01010101 +
#672
b10000101 (
b01000000 )
b00111111 *
b01010110 +
#674
b10000010 (
b00111101 )
b01000000 *
b01010111 +
#676
b01111110 (
b00111011 )
b01000001 *
b01011000 +
#678
b01111011 (
b00111000 )
b01000010 *
b01011001 +
#680
b01111000 (
b00110101 )
b01000011 *
b01011010 +
#682
b01110101 (
b00110011 )
b01000100 *
b01011011 +
#684
b01110010 (
b00110000 )
b01000101 *
b01011100 +
#686
b01101111 (
b00101110 )
b01000110 *
b01011101 +
#688
b01101100 (
b00101100 )
b01000111 *
b01011110 +
#690
b01101001 (
b00101001 )
b01001000 *
b01011111 +
#692
b01100110 (
b00100111 )
b01001001 *
b01100000 +
#694
b01100011 (
b00100101 )
b01001010 *
b01100001 +
#696
b01100000 (
b00100011 )
b01001011 *
b01100010 +
#698
b01011101 (
b00100000 )
b01001100 *
b01100011 +
#700
b01011010 (
b00011110 )
b01001101 *
b01100100 +
#702
b01010111 (
b00011100 )
b01001110 *
b01100101 +
#704
b01010100 (
b00011010 )
b01001111 *
b01100110 +
#706
b01010001 (
b00011000 )
b01010000 *
b01100111 +
#708
b01001110 (
b00010111 )
b01010001 *
b01101000 +
#710
b01001011 (
b00010101 )
b01010010 *
b01101001 +
#712
b01001000 (
b00010011 )
b01010011 *
b01101010 +
#714
b01000101 (
b00010010 )
b01010100 *
b01101011 +
#716
b01000011 (
b00010000 )
b01010101 *
b01101100 +
#718
b01000000 (
b00001110 )
b01010110 *
b01101101 +
#720
b00111101 (
b00001101 )
b01010111 *
b01101110 +
#722
b00111011 (
b00001100 )
b01011000 *
b01101111 +
#724
b00111000 (
b00001010 )
b01011001 *
b01110000 +
#726
b00110101 (
b00001001 )
b01011010 *
b01110001 +
#728
b00110011 (
b00001000 )
b01011011 *
b01110010 +
#730
b00110000 (
b00000111 )
b01011100 *
b01110011 +
#732
b00101110 (
b00000110 )
b01011101 *
b01110100 +
#734
b00101100 (
b00000101 )
b01011110 *
b01110101 +
#736
b00101001 (
b00000100 )
b01011111 *
b01110110 +
#738
b00100111 (
b00000011 )
b01100000 *
b01110111 +
#740
b00100101 (
b01100001 *
b01111000 +
#742
b00100011 (
b00000010 )
b01100010 *
b01111001 +
#744
b00100000 (
b00000001 )
b01100011 *
b01111010 +
#746
b00011110 (
b01100100 *
b01111011 +
#748
b00011100 (
b00000000 )
b01100101 *
b01111100 +
#750
b00011010 (
b01100110 *
b01111101 +
#752
b00011000 (
b01100111 *
b01111110 +
#754
b00010111 (
b01101000 *
b01111111 +
#756
b00010101 (
b01101001 *
b10000000 +
#758
b00010011 (
b01101010 *
b10000001 +
#760
b00010010 (
b01101011 *
b10000010 +
#762
b00010000 (
b01101100 *
b10000011 +
#764
b00001110 (
b01101101 *
b10000100 +
#766
b00001101 (
b01101110 *
b10000101 +
#768
b00001100 (
b01101111 *
b10000110 +
#770
b00001010 (
b00000001 )
b01110000 *
b10000111 +
#772
b00001001 (
b01110001 *
b10001000 +
#774
b00001000 (
b00000010 )
b01110010 *
b10001001 +
#776
b00000111 (
b00000011 )
b01110011 *
b10001010 +
#778
b00000110 (
b01110100 *
b10001011 +
#780
b00000101 (
b00000100 )
b01110101 *
b10001100 +
#782
b00000100 (
b00000101 )
b01110110 *
b10001101 +
#784
b00000011 (
b00000110 )
b01110111 *
b10001110 +
#786
b00000111 )
b01111000 *
b10001111 +
#788
b00000010 (
b00001000 )
b01111001 *
b10010000 +
#790
b00000001 (
b00001001 )
b01111010 *
b10010001 +
#792
b00001010 )
b01111011 *
b10010010 +
#794
b00000000 (
b00001100 )
b01111100 *
b10010011 +
#796
b00001101 )
b01111101 *
b10010100 +
#798
b00001110 )
b01111110 *
b10010101 +
#800
b00010000 )
b01111111 *
b10010110 +
#802
b00010010 )
b10000000 *
b10010111 +
#804
b00010011 )
b10000001 *
b10011000 +
#806
b00010101 )
b10000010 *
b10011001 +
#808
b00010111 )
b10000011 *
b10011010 +
#810
b00011000 )
b10000100 *
b10011011 +
#812
b00011010 )
b10000101 *
b10011100 +
#814
b00011100 )
b10000110 *
b10011101 +
#816
b00000001 (
b00011110 )
b10000111 *
b10011110 +
#818
b00100000 )
b10001000 *
b10011111 +
#820
b00000010 (
b00100011 )
b10001001 *
b10100000 +
#822
b00000011 (
b00100101 )
b10001010 *
b10100001 +
#824
b00100111 )
b10001011 *
b10100010 +
#826
b00000100 (
b00101001 )
b10001100 *
b10100011 +
#828
b00000101 (
b00101100 )
b10001101 *
b10100100 +
#830
b00000110 (
b00101110 )
b10001110 *
b10100101 +
#832
b00000111 (
b00110000 )
b10001111 *
b10100110 +
#834
b00001000 (
b00110011 )
b10010000 *
b10100111 +
#836
b00001001 (
b00110101 )
b10010001 *
b10101000 +
#838
b00001010 (
b00111000 )
b10010010 *
b10101001 +
#840
b00001100 (
b00111011 )
b10010011 *
b10101010 +
#842
b00001101 (
b00111101 )
b10010100 *
b10101011 +
#844
b00001110 (
b01000000 )
b10010101 *
b10101100 +
#846
b00010000 (
b01000011 )
b10010110 *
b10101101 +
#848
b00010010 (
b01000101 )
b10010111 *
b10101110 +
#850
b00010011 (
b01001000 )
b10011000 *
b10101111 +
#852
b00010101 (
b01001011 )
b10011001 *
b10110000 +
#854
b00010111 (
b01001110 )
b10011010 *
b10110001 +
#856
b00011000 (
b01010001 )
b10011011 *
b10110010 +
#858
b00011010 (
b01010100 )
b10011100 *
b10110011 +
#860
b00011100 (
b01010111 )
b10011101 *
b10110100 +
#862
b00011110 (
b01011010 )
b10011110 *
b10110101 +
#864
b00100000 (
b01011101 )
b10011111 *
b10110110 +
#866
b00100011 (
b01100000 )
b10100000 *
b10110111 +
#868
b00100101 (
b01100011 )
b10100001 *
b10111000 +
#870
b00100111 (
b01100110 )
b10100010 *
b10111001 +
#872
b00101001 (
b01101001 )
b10100011 *
b10111010 +
#874
b00101100 (
b01101100 )
b10100100 *
b10111011 +
#876
b00101110 (
b01101111 )
b10100101 *
b10111100 +
#878
b00110000 (
b01110010 )
b10100110 *
b10111101 +
#880
b00110011 (
b01110101 )
b10100111 *
b10111110 +
#882
b00110101 (
b01111000 )
b10101000 *
b10111111 +
#884
b00111000 (
b01111011 )
b10101001 *
b11000000 +
#886
b00111011 (
b01111111 )
b10101010 *
b11000001 +
#888
b00111101 (
b10000010 )
b10101011 *
b11000010 +
#890
b01000000 (
b10000101 )
b10101100 *
b11000011 +
#892
b01000011 (
b10001000 )
b10101101 *
b11000100 +
#894
b01000101 (
b10001011 )
b10101110 *
b11000101 +
#896
b01001000 (
b10001110 )
b10101111 *
b11000110 +
#898
b01001011 (
b10010001 )
b10110000 *
b11000111 +
#900
b01001110 (
b10010100 )
b10110001 *
b11001000 +
#902
b01010001 (
b10010111 )
b10110010 *
b11001001 +
#904
b01010100 (
b10011010 )
b10110011 *
b11001010 +
#906
b01010111 (
b10011101 )
b10110100 *
b11001011 +
#908
b01011010 (
b10100000 )
b10110101 *
b11001100 +
#910
b01011101 (
b10100011 )
b10110110 *
b11001101 +
#912
b01100000 (
b10100110 )
b10110111 *
b11001110 +
#914
b01100011 (
b10101001 )
b10111000 *
b11001111 +
